TAIL/__init__.py
TAIL/categorise.py
TAIL/const.py
TAIL/dummy_data.py
TAIL/model.py
TAIL/parser.py
TAIL/schedule.py
TAIL/tail.py
TAIL/units.py
TAIL/ventilation.py
test/__init__.py
test/test_model.py
test/test_unit_conversion.py
tail_rating_py-0.1.3.dist-info/LICENSE
tail_rating_py-0.1.3.dist-info/METADATA
tail_rating_py-0.1.3.dist-info/WHEEL
tail_rating_py-0.1.3.dist-info/top_level.txt
tail_rating_py-0.1.3.dist-info/RECORD
