Metadata-Version: 2.1
Name: tail-rating-py
Version: 0.1.3
Summary: A Python package designed to assess TAIL (Thermal, Acoustic, Indoor Air Quality, and Lighting) for buildings.
Home-page: 
Author: Bruno Adam
Author-email: bruno.adam@pm.me
License: GNU General Public License v3 (GPLv3)
Keywords: tail thermal acoustic indoor air quality lighting
Classifier: Programming Language :: Python :: 3
Classifier: License :: OSI Approved :: GNU General Public License v3 (GPLv3)
Classifier: Operating System :: OS Independent
Requires-Python: >=3.7
License-File: LICENSE
Requires-Dist: holidays
Requires-Dist: pandas
Requires-Dist: numpy
Requires-Dist: matplotlib
Requires-Dist: pydantic
Requires-Dist: ipykernel
Requires-Dist: pint
Requires-Dist: setuptools
Requires-Dist: wheel
Requires-Dist: twine
